{"id":532,"count":10,"description":"Wysokiej jakości kosze na śmieci przeznaczone do przestrzeni publicznej. Sprawdzą się zarówno w parkach, przy przystankach, na placach zabaw oraz na ulicach miejskich. Oferujemy także ozdobne kosze charakteryzujące się przyjemnym designem.","link":"https://comes.pl/kategoria/urzadzenia-komunalne/kosze-na-smieci/","name":"Kosze","slug":"kosze-na-smieci","taxonomy":"product_cat","parent":187,"meta":[],"acf":[],"_links":{"self":[{"href":"https://comes.pl/wp-json/wp/v2/product_cat/532"}],"collection":[{"href":"https://comes.pl/wp-json/wp/v2/product_cat"}],"about":[{"href":"https://comes.pl/wp-json/wp/v2/taxonomies/product_cat"}],"up":[{"embeddable":true,"href":"https://comes.pl/wp-json/wp/v2/product_cat/187"}],"wp:post_type":[{"href":"https://comes.pl/wp-json/wp/v2/product?product_cat=532"}],"curies":[{"name":"wp","href":"https://api.w.org/{rel}","templated":true}]}}